bsconv/__init__.py
bsconv/datasets.py
bsconv/utils.py
bsconv/pytorch/__init__.py
bsconv/pytorch/common.py
bsconv/pytorch/mobilenet.py
bsconv/pytorch/modules.py
bsconv/pytorch/profile.py
bsconv/pytorch/provider.py
bsconv/pytorch/replacers.py
bsconv/pytorch/resnet.py
bsconv-0.4.0.data/scripts/bsconv_pytorch_train.py
bsconv-0.4.0.dist-info/DESCRIPTION.rst
bsconv-0.4.0.dist-info/METADATA
bsconv-0.4.0.dist-info/RECORD
bsconv-0.4.0.dist-info/WHEEL
bsconv-0.4.0.dist-info/metadata.json
bsconv-0.4.0.dist-info/top_level.txt
