Metadata-Version: 2.0
Name: bsconv
Version: 0.4.0
Summary: Reference implementation for Blueprint Separable Convolutions (BSConv)
Home-page: https://github.com/zeiss-microscopy/BSConv
Author: UNKNOWN
Author-email: UNKNOWN
License: BSD 3-Clause Clear License
Platform: UNKNOWN
